pydbeamer/__init__.py
pydbeamer/baseA4.tex
pydbeamer/basebeamer.tex
pydbeamer/pydbeamer.pyc
pydbeamer/pythonhighlight.sty
pydbeamer-0.4.2.dist-info/LICENSE.txt
pydbeamer-0.4.2.dist-info/METADATA
pydbeamer-0.4.2.dist-info/WHEEL
pydbeamer-0.4.2.dist-info/top_level.txt
pydbeamer-0.4.2.dist-info/RECORD
