Metadata-Version: 2.1
Name: pydbeamer
Version: 0.4.2
Summary: A Simple Tool for Generating Tex
Home-page: https://pypi.org/manage/project/pydbeamer/releases/
Author: David Dai
Author-email: daimw@swufe.edu.cn
Project-URL: Bug Tracker, https://pypi.org/manage/project/pydbeamer/releases/
Classifier: Programming Language :: Python :: 3
Classifier: License :: OSI Approved :: MIT License
Classifier: Operating System :: OS Independent
Requires-Python: >3.7
License-File: LICENSE.txt
